{"title":"Synthetic Data","markdown":{"yaml":{"title":"Synthetic Data","author":"Viraj R. Chordiya","date":"05/01/2023","output":{"html_document":{"code_folding":"hide"}},"editor_options":{"chunk_output_type":"console"}},"headingText":"Data","containsRefs":false,"markdown":"\n\n\n\nWe use a mix of administrative and survey data to estimate the causal link between the program and the outcomes of interest. We conduct weekly survey for a 4-week period to measure the household level weekly payments received, time spent (in minutes) at the PoS, days between work is completed and payment is received, and corruption incidences. We compare the weekly payments received to the official disbursement data to estimate the household level leakage in the system, the amount lost in inefficiencies or corruptions. Alongside, we collect data on household characteristics like number of children, number of females in the household, household literacy rate, religion, assets like farmland, and household head age and gender. \n"},"formats":{"html":{"execute":{"fig-width":7,"fig-height":5,"fig-format":"retina","fig-dpi":96,"df-print":"default","error":false,"eval":true,"cache":null,"freeze":false,"echo":true,"output":{"html_document":{"code_folding":"hide"}},"warning":true,"include":true,"keep-md":false,"keep-ipynb":false,"ipynb":null,"enabled":null,"daemon":null,"daemon-restart":false,"debug":false,"ipynb-filters":[],"engine":"knitr"},"render":{"keep-tex":false,"keep-source":false,"keep-hidden":false,"prefer-html":false,"output-divs":true,"output-ext":"html","fig-align":"default","fig-pos":null,"fig-env":null,"code-fold":"none","code-overflow":"scroll","code-link":false,"code-line-numbers":false,"code-tools":false,"tbl-colwidths":"auto","merge-includes":true,"latex-auto-mk":true,"latex-auto-install":true,"latex-clean":true,"latex-max-runs":10,"latex-makeindex":"makeindex","latex-makeindex-opts":[],"latex-tlmgr-opts":[],"latex-input-paths":[],"latex-output-dir":null,"link-external-icon":false,"link-external-newwindow":false,"self-contained-math":false,"format-resources":[]},"pandoc":{"standalone":true,"wrap":"none","default-image-extension":"png","to":"html","css":["styles.css"],"toc":true,"output-file":"synthetic_data.html"},"language":{},"metadata":{"lang":"en","fig-responsive":true,"quarto-version":"1.2.335","editor":"visual","theme":"minty","title":"Synthetic Data","author":"Viraj R. Chordiya","date":"05/01/2023","editor_options":{"chunk_output_type":"console"}},"extensions":{"book":{"multiFile":true}}}}}